agenthub/core/__init__.py
agenthub/core/base.py
agenthub_core-0.0.4.dist-info/METADATA
agenthub_core-0.0.4.dist-info/WHEEL
agenthub_core-0.0.4.dist-info/top_level.txt
agenthub_core-0.0.4.dist-info/RECORD
