Metadata-Version: 2.1
Name: agenthub-core
Version: 0.0.4
Summary: AgentHub core package
Author-email: Jacob Weiss <jaweiss2305@gmail.com>
Project-URL: homepage, https://github.com/jacobweiss2305/agenthub
Project-URL: repository, https://github.com/jacobweiss2305/agenthub/tree/main/packages/core
Requires-Python: >=3.7
